{
  "@context": "http://purl.org/pearson/content/v1/ctx/metadata/envelope",
  "@type": "Envelope",
  "metadata": {
    "bookTitle": "Sociology",
    "keywords": [
      "Macionis 15e",
      "ch15",
      "Rudowski"
    ],
    "extendedMetadata": [
      {
        "name": "ISBN",
        "value": "0133795012"
      },
      {
        "name": "M",
        "value": "c01"
      },
      {
        "name": "assessment_title",
        "value": "Chapter Quiz: Aging and the Elderly"
      },
      {
        "name": "Topic",
        "value": "Growing Old: Biology and Culture"
      },
      {
        "name": "chapterTitle",
        "value": "Aging and the Elderly"
      },
      {
        "name": "item_title",
        "value": "0133795012_John J. Macionis_ch15_c01_q0003"
      },
      {
        "name": "questionlayout",
        "value": "1"
      },
      {
        "name": "CH",
        "value": "15"
      },
      {
        "name": "Difficulty",
        "value": "Difficult"
      },
      {
        "name": "Objective",
        "value": "L.O. 15.2: Describe age stratification in global context."
      },
      {
        "name": "shuffle_choices",
        "value": "Yes"
      }
    ],
    "subject": [
      "Sociology"
    ],
    "contentTypeTier2": [
      "AssessmentItem"
    ],
    "contentTypeTier1": "Assessment",
    "format": [
      "application/vnd.pearson.sanvan.v1.activity"
    ],
    "version": "1.0",
    "guid": "bb12192b-9caa-40b5-b423-68f65ab5f071",
    "bookAuthor": "John J. Macionis",
    "title": "CE.15.07 Growing Old Biology And Culture Apply L.O. 15.2",
    "educationalAlignment": [
      "http://purl.org/pearson/objectives/183725473384362"
    ]
  },
  "body": {
    "description": "CE.15.07, Growing Old: Biology and Culture, Apply, L.O. 15.2",
    "containerConfig": [
      {
        "description": "CE.15.07, Growing Old: Biology and Culture, Apply, L.O. 15.2",
        "containerId": "target1",
        "brixConfig": [
          {
            "bricId": "q1",
            "bricType": "MultipleChoiceQuestion",
            "config": {
              "id": "QUE57917",
              "question": "As you would expect a __________ to do, Jairdin investigates how people change as they grow old as well as the different ways in which societies around the world define old age.\n\u003cbr /\u003e",
              "order": "randomized",
              "presenterType": "RadioGroup",
              "presenterConfig": {
                "numberFormat": "none"
              },
              "choices": [
                {
                  "answerKey": "answer_1",
                  "content": "psychologist"
                },
                {
                  "answerKey": "answer_2",
                  "content": "psychoanalyst"
                },
                {
                  "answerKey": "answer_3",
                  "content": "gerontologist"
                },
                {
                  "answerKey": "answer_4",
                  "content": "biologist"
                }
              ]
            },
            "answerKey": {
              "assessmentType": "multiplechoice",
              "answers": {
                "answer_3": {
                  "score": 1.0,
                  "response": ""
                },
                "answer_2": {
                  "score": 0.0,
                  "response": "Consider this: These professionals work in many disciplines, including medicine, psychology, and sociology.\n\u003cbr /\u003eRefer to Learning Objective 15.2 : Describe age stratification in global context."
                },
                "answer_1": {
                  "score": 0.0,
                  "response": "Consider this: These professionals work in many disciplines, including medicine, psychology, and sociology.\n\u003cbr /\u003eRefer to Learning Objective 15.2 : Describe age stratification in global context."
                },
                "answer_4": {
                  "score": 0.0,
                  "response": "Consider this: These professionals work in many disciplines, including medicine, psychology, and sociology.\n\u003cbr /\u003eRefer to Learning Objective 15.2 : Describe age stratification in global context."
                }
              }
            },
            "configFixup": [
              {
                "name": "questionId",
                "type": "set-property",
                "value": {
                  "domain": "info",
                  "refId": "sequenceNodeKey",
                  "type": "ref"
                }
              },
              {
                "name": "maxAttempts",
                "type": "set-property",
                "value": {
                  "domain": "info",
                  "refId": "maxAttempts",
                  "type": "ref"
                }
              }
            ]
          }
        ],
        "hookupActions": [
          {
            "description": "Hookup the submit manager to evaluate answers",
            "methodName": "handleRequestsFrom",
            "type": "method-call",
            "args": [
              {
                "domain": "brix",
                "refId": "q1",
                "type": "ref"
              }
            ],
            "instance": {
              "type": "submit-manager"
            }
          },
          {
            "description": "Draw the question",
            "methodName": "draw",
            "type": "method-call",
            "args": [
              {
                "selector": "#target1",
                "type": "d3select"
              }
            ],
            "instance": {
              "domain": "brix",
              "refId": "q1",
              "type": "ref"
            }
          }
        ]
      }
    ],
    "title": "CE.15.07 Growing Old Biology And Culture Apply L.O. 15.2"
  }
}