{
  "@context": "http://purl.org/pearson/content/v1/ctx/metadata/envelope",
  "@type": "Envelope",
  "metadata": {
    "bookTitle": "Listen To This",
    "keywords": [
      "Bonds 3e",
      "ch 07",
      "Rudowski"
    ],
    "extendedMetadata": [
      {
        "name": "Page-Reference",
        "value": "66"
      },
      {
        "name": "ISBN",
        "value": "0133794636"
      },
      {
        "name": "M",
        "value": "m01"
      },
      {
        "name": "assessment_title",
        "value": "Quiz: Thomas Weelkes, âSince Robin Hoodâ"
      },
      {
        "name": "Topic",
        "value": "Texture: Polyphony in Three Voices"
      },
      {
        "name": "chapterTitle",
        "value": "The Renaissance: ca. 1425â1600"
      },
      {
        "name": "module",
        "value": "Thomas Weelkes, âSince Robin Hoodâ"
      },
      {
        "name": "item_title",
        "value": "0133794636_Mark Evan Bonds_ch07_m01_q0003"
      },
      {
        "name": "questionlayout",
        "value": "1"
      },
      {
        "name": "CH",
        "value": "7"
      },
      {
        "name": "Objective",
        "value": "LO 7.2 Situate the Morris dance and its music in Renaissance culture."
      },
      {
        "name": "shuffle_choices",
        "value": "Yes"
      }
    ],
    "subject": [
      "Music"
    ],
    "contentTypeTier2": [
      "AssessmentItem"
    ],
    "contentTypeTier1": "Assessment",
    "format": [
      "application/vnd.pearson.sanvan.v1.activity"
    ],
    "version": "1.0",
    "guid": "01864126-1701-43e7-9d2c-b42a89ba3d87",
    "bookAuthor": "Mark Evan Bonds",
    "title": "Ch07 Post Fact 03",
    "educationalAlignment": [
      "http://purl.org/pearson/objectives/183725473384362"
    ]
  },
  "body": {
    "description": "ch07_post_fact_03",
    "containerConfig": [
      {
        "description": "ch07_post_fact_03",
        "containerId": "target1",
        "brixConfig": [
          {
            "bricId": "q1",
            "bricType": "MultipleChoiceQuestion",
            "config": {
              "id": "QUE63530",
              "question": "Which voice part contained a melody well known during Weelkes\u0027s time?\n\u003cbr /\u003e",
              "order": "randomized",
              "presenterType": "RadioGroup",
              "presenterConfig": {
                "numberFormat": "none"
              },
              "choices": [
                {
                  "answerKey": "answer_1",
                  "content": "the highest voice part"
                },
                {
                  "answerKey": "answer_2",
                  "content": "the lowest voice part"
                },
                {
                  "answerKey": "answer_3",
                  "content": "the middle voice part"
                },
                {
                  "answerKey": "answer_4",
                  "content": "all three voice parts"
                }
              ]
            },
            "answerKey": {
              "assessmentType": "multiplechoice",
              "answers": {
                "answer_3": {
                  "score": 0.0,
                  "response": " LO 7.2 Situate the Morris dance and its music in Renaissance culture."
                },
                "answer_2": {
                  "score": 0.0,
                  "response": " LO 7.2 Situate the Morris dance and its music in Renaissance culture."
                },
                "answer_1": {
                  "score": 1.0,
                  "response": ""
                },
                "answer_4": {
                  "score": 0.0,
                  "response": " LO 7.2 Situate the Morris dance and its music in Renaissance culture."
                }
              }
            },
            "configFixup": [
              {
                "name": "questionId",
                "type": "set-property",
                "value": {
                  "domain": "info",
                  "refId": "sequenceNodeKey",
                  "type": "ref"
                }
              },
              {
                "name": "maxAttempts",
                "type": "set-property",
                "value": {
                  "domain": "info",
                  "refId": "maxAttempts",
                  "type": "ref"
                }
              }
            ]
          }
        ],
        "hookupActions": [
          {
            "description": "Hookup the submit manager to evaluate answers",
            "methodName": "handleRequestsFrom",
            "type": "method-call",
            "args": [
              {
                "domain": "brix",
                "refId": "q1",
                "type": "ref"
              }
            ],
            "instance": {
              "type": "submit-manager"
            }
          },
          {
            "description": "Draw the question",
            "methodName": "draw",
            "type": "method-call",
            "args": [
              {
                "selector": "#target1",
                "type": "d3select"
              }
            ],
            "instance": {
              "domain": "brix",
              "refId": "q1",
              "type": "ref"
            }
          }
        ]
      }
    ],
    "title": "Ch07 Post Fact 03"
  }
}