{
  "@context": "http://purl.org/pearson/content/v1/ctx/metadata/envelope",
  "@type": "Envelope",
  "metadata": {
    "bookTitle": "Public Speaking: An Audience-Centered Approach",
    "keywords": [
      "Beebe 9e",
      "ch 06",
      "Rudowski"
    ],
    "extendedMetadata": [
      {
        "name": "Page-Reference",
        "value": "114"
      },
      {
        "name": "ISBN",
        "value": "0133859703"
      },
      {
        "name": "M",
        "value": "m01"
      },
      {
        "name": "assessment_title",
        "value": "Quiz: Select and Narrow Your Topic"
      },
      {
        "name": "Topic",
        "value": "Select and Narrow Your Topic"
      },
      {
        "name": "chapterTitle",
        "value": "Developing Your Speech"
      },
      {
        "name": "module",
        "value": "Select and Narrow Your Topic"
      },
      {
        "name": "item_title",
        "value": "0133859703_Steven A. Beebe; Susan J. Beebe_ch06_m01_q0003"
      },
      {
        "name": "questionlayout",
        "value": "1"
      },
      {
        "name": "CH",
        "value": "6"
      },
      {
        "name": "Difficulty",
        "value": "Moderate"
      },
      {
        "name": "Objective",
        "value": "6.1 Select and narrow a topic for a speech that is appropriate to the audience, the occasion, the ti"
      },
      {
        "name": "shuffle_choices",
        "value": "Yes"
      }
    ],
    "subject": [
      "Communication"
    ],
    "contentTypeTier2": [
      "AssessmentItem"
    ],
    "contentTypeTier1": "Assessment",
    "format": [
      "application/vnd.pearson.sanvan.v1.activity"
    ],
    "version": "1.0",
    "guid": "6ff95474-f8ad-4cc7-b2ce-12330e82b7aa",
    "bookAuthor": "Steven A. Beebe; Susan J. Beebe",
    "title": "Pre.06.06 Select And Narrow Your Topic Apply LO 6.1",
    "educationalAlignment": [
      "http://purl.org/pearson/objectives/183725473384362"
    ]
  },
  "body": {
    "description": "Pre.06.06 Select and Narrow Your Topic, Apply, LO 6.1",
    "containerConfig": [
      {
        "description": "Pre.06.06 Select and Narrow Your Topic, Apply, LO 6.1",
        "containerId": "target1",
        "brixConfig": [
          {
            "bricId": "q1",
            "bricType": "MultipleChoiceQuestion",
            "config": {
              "id": "QUE60176",
              "question": "In order to decide what topic she should choose for her speech, Mariel takes five minutes to write down every possible topic she can think of. What process is Mariel using to choose a topic?\n\u003cbr /\u003e",
              "order": "randomized",
              "presenterType": "RadioGroup",
              "presenterConfig": {
                "numberFormat": "none"
              },
              "choices": [
                {
                  "answerKey": "answer_1",
                  "content": "signposting"
                },
                {
                  "answerKey": "answer_2",
                  "content": "attending"
                },
                {
                  "answerKey": "answer_3",
                  "content": "brainstorming"
                },
                {
                  "answerKey": "answer_4",
                  "content": "dialogue"
                }
              ]
            },
            "answerKey": {
              "assessmentType": "multiplechoice",
              "answers": {
                "answer_3": {
                  "score": 1.0,
                  "response": ""
                },
                "answer_2": {
                  "score": 0.0,
                  "response": ""
                },
                "answer_1": {
                  "score": 0.0,
                  "response": ""
                },
                "answer_4": {
                  "score": 0.0,
                  "response": ""
                }
              }
            },
            "configFixup": [
              {
                "name": "questionId",
                "type": "set-property",
                "value": {
                  "domain": "info",
                  "refId": "sequenceNodeKey",
                  "type": "ref"
                }
              },
              {
                "name": "maxAttempts",
                "type": "set-property",
                "value": {
                  "domain": "info",
                  "refId": "maxAttempts",
                  "type": "ref"
                }
              }
            ]
          }
        ],
        "hookupActions": [
          {
            "description": "Hookup the submit manager to evaluate answers",
            "methodName": "handleRequestsFrom",
            "type": "method-call",
            "args": [
              {
                "domain": "brix",
                "refId": "q1",
                "type": "ref"
              }
            ],
            "instance": {
              "type": "submit-manager"
            }
          },
          {
            "description": "Draw the question",
            "methodName": "draw",
            "type": "method-call",
            "args": [
              {
                "selector": "#target1",
                "type": "d3select"
              }
            ],
            "instance": {
              "domain": "brix",
              "refId": "q1",
              "type": "ref"
            }
          }
        ]
      }
    ],
    "title": "Pre.06.06 Select And Narrow Your Topic Apply LO 6.1"
  }
}