{
  "@context": "http://purl.org/pearson/content/v1/ctx/metadata/envelope",
  "@type": "Envelope",
  "metadata": {
    "bookTitle": "Sociology: A Down-to-Earth Approach",
    "keywords": [
      "Henslin 12e",
      "ch 15",
      "Rudowski"
    ],
    "extendedMetadata": [
      {
        "name": "ISBN",
        "value": "0133795004"
      },
      {
        "name": "M",
        "value": "c01"
      },
      {
        "name": "assessment_title",
        "value": "Chapter Quiz: Politics"
      },
      {
        "name": "Topic",
        "value": "Power, Authority, and Violence"
      },
      {
        "name": "chapterTitle",
        "value": "Politics"
      },
      {
        "name": "item_title",
        "value": "0133795004_James M. Henslin_ch15_c01_q0010"
      },
      {
        "name": "CH",
        "value": "15"
      },
      {
        "name": "Objective",
        "value": "LO: 15.2: Contrast power, authority, and violence; compare traditional, rational-legal, and charismatic authority; explain authority as an ideal type."
      },
      {
        "name": "shuffle_choices",
        "value": "Yes"
      }
    ],
    "subject": [
      "Sociology"
    ],
    "contentTypeTier2": [
      "AssessmentItem"
    ],
    "contentTypeTier1": "Assessment",
    "format": [
      "application/vnd.pearson.sanvan.v1.activity"
    ],
    "version": "1.0",
    "guid": "77a51415-8b02-4c9a-b6c6-feb50305c715",
    "bookAuthor": "James M. Henslin",
    "title": "CE 15 03",
    "educationalAlignment": [
      "http://purl.org/pearson/objectives/183725473384362"
    ]
  },
  "body": {
    "description": "CE_15_03",
    "containerConfig": [
      {
        "description": "CE_15_03",
        "containerId": "target1",
        "brixConfig": [
          {
            "bricId": "q1",
            "bricType": "MultipleChoiceQuestion",
            "config": {
              "id": "QUE59636",
              "question": "What one factor makes coercion different from authority?\n\u003cbr /\u003e",
              "order": "randomized",
              "presenterType": "RadioGroup",
              "presenterConfig": {
                "numberFormat": "none"
              },
              "choices": [
                {
                  "answerKey": "answer_1",
                  "content": "Coercion is the ability to exercise authority."
                },
                {
                  "answerKey": "answer_2",
                  "content": "Authority and coercion are really the same."
                },
                {
                  "answerKey": "answer_3",
                  "content": "Coercion is considered illegitimate power."
                },
                {
                  "answerKey": "answer_4",
                  "content": "Authority is considered illegitimate power."
                }
              ]
            },
            "answerKey": {
              "assessmentType": "multiplechoice",
              "answers": {
                "answer_3": {
                  "score": 1.0,
                  "response": "That’s correct!"
                },
                "answer_2": {
                  "score": 0.0,
                  "response": "sider this: legitimate power is called authority. LO 15.2 Contrast power, authority, and violence; compare traditional, rational–legal, and charismatic authority; explain authority as an ideal type."
                },
                "answer_1": {
                  "score": 0.0,
                  "response": "sider this: legitimate power is called authority. LO 15.2 Contrast power, authority, and violence; compare traditional, rational–legal, and charismatic authority; explain authority as an ideal type."
                },
                "answer_4": {
                  "score": 0.0,
                  "response": "sider this: legitimate power is called authority. LO 15.2 Contrast power, authority, and violence; compare traditional, rational–legal, and charismatic authority; explain authority as an ideal type."
                }
              }
            },
            "configFixup": [
              {
                "name": "questionId",
                "type": "set-property",
                "value": {
                  "domain": "info",
                  "refId": "sequenceNodeKey",
                  "type": "ref"
                }
              },
              {
                "name": "maxAttempts",
                "type": "set-property",
                "value": {
                  "domain": "info",
                  "refId": "maxAttempts",
                  "type": "ref"
                }
              }
            ]
          }
        ],
        "hookupActions": [
          {
            "description": "Hookup the submit manager to evaluate answers",
            "methodName": "handleRequestsFrom",
            "type": "method-call",
            "args": [
              {
                "domain": "brix",
                "refId": "q1",
                "type": "ref"
              }
            ],
            "instance": {
              "type": "submit-manager"
            }
          },
          {
            "description": "Draw the question",
            "methodName": "draw",
            "type": "method-call",
            "args": [
              {
                "selector": "#target1",
                "type": "d3select"
              }
            ],
            "instance": {
              "domain": "brix",
              "refId": "q1",
              "type": "ref"
            }
          }
        ]
      }
    ],
    "title": "CE 15 03"
  }
}