{
  "@context": "http://purl.org/pearson/content/v1/ctx/metadata/envelope",
  "@type": "Envelope",
  "metadata": {
    "guid": "d4afacb9-8c7e-422f-a305-930114d77644",
    "bookAuthor": "John J. Macionis",
    "bookTitle": "Sociology",
    "title": "Quiz: Work in the Postindustrial U.S. Economy",
    "keywords": [
      "Macionis 15e",
      "ch16",
      "Rudowski",
      "MQ16.3"
    ],
    "extendedMetadata": [
      {
        "name": "ISBN",
        "value": "0133795012"
      },
      {
        "name": "M",
        "value": "m03"
      },
      {
        "name": "qmd_absolutescore_min",
        "value": "0"
      },
      {
        "name": "assessment_title",
        "value": "Quiz: Work in the Postindustrial U.S. Economy"
      },
      {
        "name": "assignmentTitle",
        "value": "Quiz: Work in the Postindustrial U.S. Economy"
      },
      {
        "name": "Topic",
        "value": "Work in the Postindustrial U.S. Economy"
      },
      {
        "name": "qst_type",
        "value": "MCSS text without media"
      },
      {
        "name": "qmd_HighStake",
        "value": "True"
      },
      {
        "name": "qst_html_template",
        "value": "mcssall"
      },
      {
        "name": "chapterTitle",
        "value": "The Economy and Work"
      },
      {
        "name": "module",
        "value": "Work in the Postindustrial U.S. Economy"
      },
      {
        "name": "qmd_maximumscore",
        "value": "1"
      },
      {
        "name": "qmd_QuestionTime",
        "value": "0"
      },
      {
        "name": "qmd_version",
        "value": "2.0"
      },
      {
        "name": "qmd_Hidden",
        "value": "False"
      },
      {
        "name": "questionlayout",
        "value": "1"
      },
      {
        "name": "qmd_toolvendor",
        "value": "Excelsoft"
      },
      {
        "name": "CH",
        "value": "16"
      },
      {
        "name": "qmd_penaltyvalue",
        "value": "0.0"
      },
      {
        "name": "qmd_status",
        "value": "Normal"
      },
      {
        "name": "qmd_itemtype",
        "value": "Multiple Choice Static"
      },
      {
        "name": "qmd_absolutescore_max",
        "value": "100"
      },
      {
        "name": "Objective",
        "value": "L.O. 16.3: Analyze patterns of employment and unemployment in the United States."
      },
      {
        "name": "shuffle_choices",
        "value": "Yes"
      }
    ],
    "subject": [
      "Sociology"
    ],
    "contentTypeTier2": [
      "Assignment"
    ],
    "contentTypeTier1": "Assessment",
    "version": "1.0"
  },
  "body": {
    "guid": "d4afacb9-8c7e-422f-a305-930114d77644",
    "title": "Quiz: Work in the Postindustrial U.S. Economy",
    "@context": "http://purl.org/pearson/paf/v1/ctx/core/StructuredAssignment",
    "@type": "StructuredAssignment",
    "assignmentContents": {
      "@contentType": "application/vnd.pearson.paf.v1.assignment+json",
      "binding": [
        {
          "guid": "9a536554-e768-4b7e-a2f5-0e617bb0fa06",
          "activityTitle": "Pre.16.03 Work In The Postindustrial U.S. Economy Apply L.O. 16.3",
          "activityFormat": "application/vnd.pearson.sanvan.v1.activity",
          "credit": "ForCredit",
          "boundActivity": "{SERVER}/paf-repo/resources/activities/9a536554-e768-4b7e-a2f5-0e617bb0fa06",
          "bindingIndex": 0.0
        },
        {
          "guid": "35b1c77a-18b4-4bbc-b18c-84c4ef569128",
          "activityTitle": "Pre.16.13 Work In The Postindustrial U.S. Economy Apply L.O. 16.3",
          "activityFormat": "application/vnd.pearson.sanvan.v1.activity",
          "credit": "ForCredit",
          "boundActivity": "{SERVER}/paf-repo/resources/activities/35b1c77a-18b4-4bbc-b18c-84c4ef569128",
          "bindingIndex": 1.0
        },
        {
          "guid": "e384e52b-4a97-43ca-af2f-01285b5670bd",
          "activityTitle": "Pre.16.15 Work In The Postindustrial U.S. Economy Remember L.O. 16.3",
          "activityFormat": "application/vnd.pearson.sanvan.v1.activity",
          "credit": "ForCredit",
          "boundActivity": "{SERVER}/paf-repo/resources/activities/e384e52b-4a97-43ca-af2f-01285b5670bd",
          "bindingIndex": 2.0
        },
        {
          "guid": "36dfb630-fd7d-4768-be69-da7d7c454c01",
          "activityTitle": "Pre.16.17 Work In The Postindustrial U.S. Economy Understand L.O. 16.3",
          "activityFormat": "application/vnd.pearson.sanvan.v1.activity",
          "credit": "ForCredit",
          "boundActivity": "{SERVER}/paf-repo/resources/activities/36dfb630-fd7d-4768-be69-da7d7c454c01",
          "bindingIndex": 3.0
        },
        {
          "guid": "c1b868a9-6270-4f41-b6b2-57dc59574a5c",
          "activityTitle": "Post.16.30 Work In The Postindustrial U.S. Economy Understand L.O. 16.3",
          "activityFormat": "application/vnd.pearson.sanvan.v1.activity",
          "credit": "ForCredit",
          "boundActivity": "{SERVER}/paf-repo/resources/activities/c1b868a9-6270-4f41-b6b2-57dc59574a5c",
          "bindingIndex": 4.0
        }
      ]
    }
  }
}