{
  "@context": "http://purl.org/pearson/content/v1/ctx/metadata/envelope",
  "@type": "Envelope",
  "metadata": {
    "guid": "46255c58-85bf-42b3-8a48-016289b373eb",
    "bookAuthor": "James M. Henslin",
    "bookTitle": "Essentials of Sociology",
    "title": "Quiz How Do Elites Maintain Stratification?",
    "keywords": [
      "Henslin 11e",
      "ch 07",
      "Rudowski",
      "MQ7.4"
    ],
    "extendedMetadata": [
      {
        "name": "ISBN",
        "value": "0133869369"
      },
      {
        "name": "M",
        "value": "m04"
      },
      {
        "name": "qmd_absolutescore_min",
        "value": "0"
      },
      {
        "name": "assessment_title",
        "value": "Quiz: How Do Elites Maintain Stratification?"
      },
      {
        "name": "assignmentTitle",
        "value": "Quiz: How Do Elites Maintain Stratification?"
      },
      {
        "name": "Topic",
        "value": "How Do Elites Maintain Stratification?"
      },
      {
        "name": "qst_type",
        "value": "MCSS text without media"
      },
      {
        "name": "qmd_HighStake",
        "value": "True"
      },
      {
        "name": "qst_html_template",
        "value": "mcssall"
      },
      {
        "name": "chapterTitle",
        "value": "Global Stratification"
      },
      {
        "name": "module",
        "value": "How Do Elites Maintain Stratification?"
      },
      {
        "name": "qmd_maximumscore",
        "value": "1"
      },
      {
        "name": "qmd_version",
        "value": "2.0"
      },
      {
        "name": "qmd_weighting",
        "value": "1.00"
      },
      {
        "name": "qmd_Hidden",
        "value": "False"
      },
      {
        "name": "questionlayout",
        "value": "1"
      },
      {
        "name": "qmd_toolvendor",
        "value": "Excelsoft"
      },
      {
        "name": "CH",
        "value": "7"
      },
      {
        "name": "qmd_penaltyvalue",
        "value": "0.0"
      },
      {
        "name": "qmd_status",
        "value": "Normal"
      },
      {
        "name": "qmd_itemtype",
        "value": "Multiple Choice Static"
      },
      {
        "name": "qmd_absolutescore_max",
        "value": "100"
      },
      {
        "name": "Objective",
        "value": "LO: 7.4: Discuss the ways that elites keep themselves in power."
      },
      {
        "name": "shuffle_choices",
        "value": "Yes"
      }
    ],
    "subject": [
      "Sociology"
    ],
    "contentTypeTier2": [
      "Assignment"
    ],
    "contentTypeTier1": "Assessment",
    "version": "1.0"
  },
  "body": {
    "guid": "46255c58-85bf-42b3-8a48-016289b373eb",
    "title": "Quiz How Do Elites Maintain Stratification?",
    "@context": "http://purl.org/pearson/paf/v1/ctx/core/StructuredAssignment",
    "@type": "StructuredAssignment",
    "assignmentContents": {
      "@contentType": "application/vnd.pearson.paf.v1.assignment+json",
      "binding": [
        {
          "guid": "93dedc1d-a9ed-4a78-a226-4d2ee3f55c5d",
          "activityTitle": "POST 07 20",
          "activityFormat": "application/vnd.pearson.sanvan.v1.activity",
          "credit": "ForCredit",
          "boundActivity": "{SERVER}/paf-repo/resources/activities/93dedc1d-a9ed-4a78-a226-4d2ee3f55c5d",
          "bindingIndex": 0.0
        },
        {
          "guid": "5ff38cfa-715f-42e6-b046-0ff3269b41ed",
          "activityTitle": "PRE 07 04",
          "activityFormat": "application/vnd.pearson.sanvan.v1.activity",
          "credit": "ForCredit",
          "boundActivity": "{SERVER}/paf-repo/resources/activities/5ff38cfa-715f-42e6-b046-0ff3269b41ed",
          "bindingIndex": 1.0
        },
        {
          "guid": "4dcf5dff-e7cf-44e6-a5f2-0bd7defa3d34",
          "activityTitle": "PRE 07 18",
          "activityFormat": "application/vnd.pearson.sanvan.v1.activity",
          "credit": "ForCredit",
          "boundActivity": "{SERVER}/paf-repo/resources/activities/4dcf5dff-e7cf-44e6-a5f2-0bd7defa3d34",
          "bindingIndex": 2.0
        },
        {
          "guid": "d8ebd939-dc34-44fd-9411-706642074141",
          "activityTitle": "POST 07 13",
          "activityFormat": "application/vnd.pearson.sanvan.v1.activity",
          "credit": "ForCredit",
          "boundActivity": "{SERVER}/paf-repo/resources/activities/d8ebd939-dc34-44fd-9411-706642074141",
          "bindingIndex": 3.0
        }
      ]
    }
  }
}