{
  "@context": "http://purl.org/pearson/content/v1/ctx/metadata/envelope",
  "@type": "Envelope",
  "metadata": {
    "bookTitle": "Psychology",
    "keywords": [
      "Ciccarelli 4e",
      "Chapter 05"
    ],
    "extendedMetadata": [
      {
        "name": "ISBN",
        "value": "0133794652"
      },
      {
        "name": "M",
        "value": "c01"
      },
      {
        "name": "assessment_title",
        "value": "Quiz: Learning"
      },
      {
        "name": "chapterTitle",
        "value": "Learning"
      },
      {
        "name": "item_title",
        "value": "0133794652_Saundra K. Ciccarelli; J. Noland White_ch05_c01_q0013"
      },
      {
        "name": "questionlayout",
        "value": "1"
      },
      {
        "name": "LearningObjective",
        "value": ""
      },
      {
        "name": "CH",
        "value": "5"
      },
      {
        "name": "shuffle_choices",
        "value": "Yes"
      }
    ],
    "subject": [
      "Psychology"
    ],
    "contentTypeTier2": [
      "AssignmentItem"
    ],
    "contentTypeTier1": "Assessment",
    "format": [
      "application/vnd.pearson.sanvan.v1.activity"
    ],
    "version": "1.0",
    "guid": "1c0f8cd1-f3c8-4f18-b098-913884668f3f",
    "bookAuthor": "Saundra K. Ciccarelli; J. Noland White",
    "title": "Ch05 ChapterQuiz5 Q13",
    "educationalAlignment": [
      "http://purl.org/pearson/objectives/183725473384362"
    ]
  },
  "body": {
    "description": "Ch05_ChapterQuiz5_Q13",
    "containerConfig": [
      {
        "description": "Ch05_ChapterQuiz5_Q13",
        "containerId": "target1",
        "brixConfig": [
          {
            "bricId": "q1",
            "bricType": "MultipleChoiceQuestion",
            "config": {
              "id": "QUE56923",
              "question": "Denise is grounded for coming home after curfew. Additionally, her parents have taken away her cell phone for a month. Losing her cell phone privileges is an example of\n\u003cbr /\u003e",
              "order": "randomized",
              "presenterType": "RadioGroup",
              "presenterConfig": {
                "numberFormat": "none"
              },
              "choices": [
                {
                  "answerKey": "answer_1",
                  "content": "negative reinforcement."
                },
                {
                  "answerKey": "answer_2",
                  "content": "punishment by application."
                },
                {
                  "answerKey": "answer_3",
                  "content": "punishment by removal."
                },
                {
                  "answerKey": "answer_4",
                  "content": "learned helplessness."
                }
              ]
            },
            "answerKey": {
              "assessmentType": "multiplechoice",
              "answers": {
                "answer_3": {
                  "score": 1.0,
                  "response": ""
                },
                "answer_2": {
                  "score": 0.0,
                  "response": "Consider this: Which term describes the weakening of a behavior by taking away something pleasant? L.O. 5.7: What is punishment and how does it differ from reinforcement?"
                },
                "answer_1": {
                  "score": 0.0,
                  "response": "Consider this: Which term describes the weakening of a behavior by taking away something pleasant? L.O. 5.7: What is punishment and how does it differ from reinforcement?"
                },
                "answer_4": {
                  "score": 0.0,
                  "response": "Consider this: Which term describes the weakening of a behavior by taking away something pleasant? L.O. 5.7: What is punishment and how does it differ from reinforcement?"
                }
              }
            },
            "configFixup": [
              {
                "name": "questionId",
                "type": "set-property",
                "value": {
                  "domain": "info",
                  "refId": "sequenceNodeKey",
                  "type": "ref"
                }
              },
              {
                "name": "maxAttempts",
                "type": "set-property",
                "value": {
                  "domain": "info",
                  "refId": "maxAttempts",
                  "type": "ref"
                }
              }
            ]
          }
        ],
        "hookupActions": [
          {
            "description": "Hookup the submit manager to evaluate answers",
            "methodName": "handleRequestsFrom",
            "type": "method-call",
            "args": [
              {
                "domain": "brix",
                "refId": "q1",
                "type": "ref"
              }
            ],
            "instance": {
              "type": "submit-manager"
            }
          },
          {
            "description": "Draw the question",
            "methodName": "draw",
            "type": "method-call",
            "args": [
              {
                "selector": "#target1",
                "type": "d3select"
              }
            ],
            "instance": {
              "domain": "brix",
              "refId": "q1",
              "type": "ref"
            }
          }
        ]
      }
    ]
  }
}